genomix_users/__init__.py
genomix_users/admin.py
genomix_users/apps.py
genomix_users/authentication.py
genomix_users/conf.py
genomix_users/filters.py
genomix_users/models.py
genomix_users/serializers.py
genomix_users/signals.py
genomix_users/urls.py
genomix_users/views.py
genomix_users/viewsets.py
genomix_users/migrations/0001_initial.py
genomix_users/migrations/__init__.py
django_genomix_users-0.5.11.dist-info/AUTHORS.rst
django_genomix_users-0.5.11.dist-info/LICENSE
django_genomix_users-0.5.11.dist-info/METADATA
django_genomix_users-0.5.11.dist-info/WHEEL
django_genomix_users-0.5.11.dist-info/top_level.txt
django_genomix_users-0.5.11.dist-info/RECORD
