Metadata-Version: 2.1
Name: django-genomix-users
Version: 0.5.11
Summary: Core library for Nexus django applications that require User accounts
Home-page: https://github.com/genomics-geek/django-genomix-users
Author: Michael A. Gonzalez
Author-email: GonzalezMA@email.chop.edu
License: MIT
Keywords: django-genomix-users
Platform: UNKNOWN
Classifier: Development Status :: 4 - Beta
Classifier: Framework :: Django :: 2.0
Classifier: Framework :: Django :: 2.1
Classifier: Framework :: Django :: 2.2
Classifier: Intended Audience :: Developers
Classifier: License :: OSI Approved :: BSD License
Classifier: Natural Language :: English
Classifier: Programming Language :: Python :: 3
Classifier: Programming Language :: Python :: 3.5
Classifier: Programming Language :: Python :: 3.6
Requires-Dist: djangorestframework (==3.10.3)
Requires-Dist: djangorestframework-jwt (==1.11.0)
Requires-Dist: django-appconf (==1.0.3)
Requires-Dist: django-filter (==2.2.0)
Requires-Dist: django-model-utils (==3.2.0)
Requires-Dist: django-python3-ldap (==0.11.2)
Requires-Dist: django-rest-auth (==0.9.5)
